django_transmeta_edw-0.7.3.dist-info/DESCRIPTION.rst
django_transmeta_edw-0.7.3.dist-info/METADATA
django_transmeta_edw-0.7.3.dist-info/RECORD
django_transmeta_edw-0.7.3.dist-info/WHEEL
django_transmeta_edw-0.7.3.dist-info/metadata.json
django_transmeta_edw-0.7.3.dist-info/top_level.txt
transmeta/__init__.py
transmeta/management/__init__.py
transmeta/management/commands/__init__.py
transmeta/management/commands/sync_transmeta_db.py
